LICENSE
MANIFEST.in
README.md
requirements.txt
setup.py
hist_loss.egg-info/PKG-INFO
hist_loss.egg-info/SOURCES.txt
hist_loss.egg-info/dependency_links.txt
hist_loss.egg-info/requires.txt
hist_loss.egg-info/top_level.txt
histloss/__init__.py
histloss/base_hist_loss.py
histloss/binomial_deviance_loss.py
histloss/continious_histogram_loss.py
histloss/earth_mover_distance_loss.py
histloss/histogram_loss.py
histloss/nll_loss.py
histloss/utils.py