Metadata-Version: 2.1
Name: hist-loss
Version: 0.0.10
Summary: Package with losses for distribution learning
Home-page: https://github.com/stat-ml/histloss
Author: Maxim Panov and Nikita Mokrov and Roman Lisov
Author-email: nikita.mokrov@skoltech.ru
License: Apache License 2.0
Platform: UNKNOWN
Classifier: Programming Language :: Python :: 3
Classifier: License :: OSI Approved :: Apache Software License
Classifier: Operating System :: OS Independent
Requires-Python: >=3.5
